demo-nbdev-temp/__init__.py
demo-nbdev-temp/_nbdev.py
demo-nbdev-temp/card.py
demo_nbdev_temp/__init__.py
demo_nbdev_temp/_nbdev.py
demo_nbdev_temp/card.py
demo_nbdev_temp-0.0.1.dist-info/LICENSE
demo_nbdev_temp-0.0.1.dist-info/METADATA
demo_nbdev_temp-0.0.1.dist-info/WHEEL
demo_nbdev_temp-0.0.1.dist-info/entry_points.txt
demo_nbdev_temp-0.0.1.dist-info/top_level.txt
demo_nbdev_temp-0.0.1.dist-info/RECORD
