Metadata-Version: 2.1
Name: demo-nbdev-temp
Version: 0.0.1
Summary: A demo
Home-page: https://github.com/hamelsmu/demo_nbdev_temp/tree/master/
Author: Hamel Husain
Author-email: hamel@example.com
License: Apache Software License 2.0
Keywords: tutorial
Platform: UNKNOWN
Classifier: Development Status :: 3 - Alpha
Classifier: Intended Audience :: Developers
Classifier: License :: OSI Approved :: Apache Software License
Classifier: Natural Language :: English
Classifier: Programming Language :: Python :: 3.6
Classifier: Programming Language :: Python :: 3.7
Classifier: Programming Language :: Python :: 3.8
Requires-Python: >=3.6
